pyins/__init__.py
pyins/_numba_integrate.py
pyins/earth.py
pyins/error_model.py
pyins/filters.py
pyins/inertial_sensor.py
pyins/kalman.py
pyins/measurements.py
pyins/sim.py
pyins/strapdown.py
pyins/transform.py
pyins/util.py
pyins/tests/test_earth.py
pyins/tests/test_error_model.py
pyins/tests/test_filters.py
pyins/tests/test_inertial_sensor.py
pyins/tests/test_kalman.py
pyins/tests/test_numba_integrate.py
pyins/tests/test_sim.py
pyins/tests/test_strapdown.py
pyins/tests/test_transform.py
pyins/tests/test_util.py
python_ins-1.0.1.dist-info/LICENSE.txt
python_ins-1.0.1.dist-info/METADATA
python_ins-1.0.1.dist-info/WHEEL
python_ins-1.0.1.dist-info/top_level.txt
python_ins-1.0.1.dist-info/RECORD
