Metadata-Version: 2.1
Name: python-ins
Version: 1.0.1
Summary: Inertial Navigation System algorithms in Python
Maintainer-email: Nikolay Mayorov <nikolay.mayorov@zoho.com>
License: MIT License
Project-URL: Homepage, https://github.com/nmayorov/pyins
Project-URL: Documentation, https://pyins.readthedocs.io
Keywords: Navigation,INS,Inertial navigation,Kalman filters
Classifier: Development Status :: 5 - Production/Stable
Classifier: Intended Audience :: Developers
Classifier: Intended Audience :: Science/Research
Classifier: Topic :: Scientific/Engineering
Classifier: License :: OSI Approved :: MIT License
Classifier: Programming Language :: Python :: 3
License-File: LICENSE.txt
Requires-Dist: numpy
Requires-Dist: numba
Requires-Dist: scipy
Requires-Dist: pandas
